rzn/__init__.py
rzn/rzn.py
rzn/sample.rzn
rzn-0.4.0.dist-info/entry_points.txt
rzn-0.4.0.dist-info/WHEEL
rzn-0.4.0.dist-info/METADATA
rzn-0.4.0.dist-info/RECORD
