Metadata-Version: 2.1
Name: rzn
Version: 0.4.0
Summary: rzn - rsync/rclone git like push/pull wrapper
License: GPL-3.0
Author: Dick Marinus
Requires-Python: >=3.10,<4.0
Classifier: License :: OSI Approved :: GNU General Public License v3 (GPLv3)
Classifier: Programming Language :: Python :: 3
Classifier: Programming Language :: Python :: 3.10
